impoasdiff/__init__.py
impoasdiff/_version.py
impoasdiff/args_manager.py
impoasdiff/diff_handler.py
impoasdiff/file_handler.py
impoasdiff/generate_diff.py
impoasdiff/utils.py
impoasdiff/templates/report_v3.html
impoasdiff-0.0.4.data/data/report_v3.html
impoasdiff-0.0.4.dist-info/METADATA
impoasdiff-0.0.4.dist-info/WHEEL
impoasdiff-0.0.4.dist-info/entry_points.txt
impoasdiff-0.0.4.dist-info/top_level.txt
impoasdiff-0.0.4.dist-info/RECORD
